odoo/addons/stock_reserve_rule/README.rst
odoo/addons/stock_reserve_rule/__init__.py
odoo/addons/stock_reserve_rule/__manifest__.py
odoo/addons/stock_reserve_rule/data/demo/product_demo.xml
odoo/addons/stock_reserve_rule/data/demo/stock_location_demo.xml
odoo/addons/stock_reserve_rule/data/demo/stock_picking_demo.xml
odoo/addons/stock_reserve_rule/data/demo/stock_reserve_rule_demo.xml
odoo/addons/stock_reserve_rule/i18n/it.po
odoo/addons/stock_reserve_rule/i18n/stock_reserve_rule.pot
odoo/addons/stock_reserve_rule/models/__init__.py
odoo/addons/stock_reserve_rule/models/stock_move.py
odoo/addons/stock_reserve_rule/models/stock_picking_type.py
odoo/addons/stock_reserve_rule/models/stock_quant.py
odoo/addons/stock_reserve_rule/models/stock_reserve_rule.py
odoo/addons/stock_reserve_rule/readme/CONFIGURE.md
odoo/addons/stock_reserve_rule/readme/CONTRIBUTORS.md
odoo/addons/stock_reserve_rule/readme/DESCRIPTION.md
odoo/addons/stock_reserve_rule/readme/USAGE.md
odoo/addons/stock_reserve_rule/security/ir.model.access.csv
odoo/addons/stock_reserve_rule/security/stock_reserve_rule_security.xml
odoo/addons/stock_reserve_rule/static/description/icon.png
odoo/addons/stock_reserve_rule/static/description/index.html
odoo/addons/stock_reserve_rule/tests/__init__.py
odoo/addons/stock_reserve_rule/tests/common.py
odoo/addons/stock_reserve_rule/tests/test_reserve_rule.py
odoo/addons/stock_reserve_rule/views/stock_reserve_rule_views.xml
odoo_addon_stock_reserve_rule-18.0.1.1.0.dist-info/METADATA
odoo_addon_stock_reserve_rule-18.0.1.1.0.dist-info/WHEEL
odoo_addon_stock_reserve_rule-18.0.1.1.0.dist-info/top_level.txt
odoo_addon_stock_reserve_rule-18.0.1.1.0.dist-info/RECORD
